{"events":[{"title":"My title 7","author":{"id":3,"name":"John Doe4","username":"user3","state":"active","avatar_url":"https://www.gravatar.com/avatar/2c75f98f3ea6cd6ee75cfbdfbb031388?s=80\u0026d=identicon","web_url":"http://localhost/user3","status_tooltip_html":null,"path":"/user3"},"iid":"2","total_time":{"seconds":0},"created_at":"4 days ago","url":"http://localhost/group2/project2/issues/2"},{"title":"My title 9","author":{"id":3,"name":"John Doe4","username":"user3","state":"active","avatar_url":"https://www.gravatar.com/avatar/2c75f98f3ea6cd6ee75cfbdfbb031388?s=80\u0026d=identicon","web_url":"http://localhost/user3","status_tooltip_html":null,"path":"/user3"},"iid":"4","total_time":{"seconds":1},"created_at":"4 days ago","url":"http://localhost/group2/project2/issues/4"}]}